[
  {
    "id": "1",
    "name": "Milk",
    "imageUrl": "https://img.rewe-static.de/0533822/7397490_digital-image.png?impolicy=s-offers&imwidth=400",
    "quantity": 2,
    "category": "Dairy",
    "comment": "Low-fat, 1 litre each, prefer brand A"
  },
  {
    "id": "2",
    "name": "Bread",
    "imageUrl": "https://img.rewe-static.de/8447075/31875450_digital-image.png?impolicy=s-offers&imwidth=400",
    "quantity": 1,
    "category": "Bakery",
    "comment": "Whole grain, large loaf, no seeds"
  },
  {
    "id": "3",
    "name": "Apples",
    "imageUrl": "https://img.rewe-static.de/7149844/34877706_digital-image.png?impolicy=s-offers&imwidth=400",
    "quantity": 6,
    "category": "Fruits",
    "comment": "Organic, medium size, prefer Gala variety"
  },
  {
    "id": "4",
    "name": "Carrots",
    "imageUrl": "https://img.rewe-static.de/7692150/39967127_digital-image.png?impolicy=s-offers&imwidth=400",
    "quantity": 5,
    "category": "Vegetables",
    "comment": "Fresh, large size, from local farm if possible"
  },
  {
    "id": "5",
    "name": "Chicken Breast",
    "imageUrl": "https://img.rewe-static.de/7087225/31533630_digital-image.png?impolicy=s-offers&imwidth=400",
    "quantity": 3,
    "category": "Meat",
    "comment": "Boneless, skinless, around 200g each"
  },
  {
    "id": "6",
    "name": "Orange Juice",
    "imageUrl": "https://img.rewe-static.de/1427496/23189253_digital-image.png?impolicy=s-offers&imwidth=400",
    "quantity": 2,
    "category": "Beverages",
    "comment": "No pulp, 1.5 litres each, prefer brand B"
  },
  {
    "id": "7",
    "name": "Chips",
    "imageUrl": "https://img.rewe-static.de/9607767/49848988_digital-image.png?impolicy=s-offers&imwidth=400",
    "quantity": 1,
    "category": "Snacks",
    "comment": "Salted, large bag, prefer brand C"
  },
  {
    "id": "8",
    "name": "Dish Soap",
    "imageUrl": "https://img.rewe-static.de/9915277/51920973_digital-image.png?impolicy=s-offers&imwidth=400",
    "quantity": 1,
    "category": "Household",
    "comment": "Lemon scented, 500ml, eco-friendly"
  },
  {
    "id": "9",
    "name": "Shampoo",
    "imageUrl": "https://img.rewe-static.de/3201421/26161976_digital-image.png?impolicy=s-offers&imwidth=400",
    "quantity": 1,
    "category": "Personal Care",
    "comment": "For dry hair, 250ml, prefer brand D"
  },
  {
    "id": "10",
    "name": "Paper Towels",
    "imageUrl": "https://img.rewe-static.de/7862584/44491891_digital-image.png?impolicy=s-offers&imwidth=400",
    "quantity": 2,
    "category": "Household",
    "comment": "Extra absorbent, 6 rolls each pack, prefer brand E"
  }
]
